SQLViaCode/SQLViaCode.py
SQLViaCode/__init__.py
SQLViaCode-0.1.2.dist-info/METADATA
SQLViaCode-0.1.2.dist-info/WHEEL
SQLViaCode-0.1.2.dist-info/top_level.txt
SQLViaCode-0.1.2.dist-info/RECORD
