Metadata-Version: 2.1
Name: SQLViaCode
Version: 0.1.2
Summary: A Python package to query SQL databases and manage backups.
Author: Afik Ratzon
Author-email: afik.ratzon@gmail.com
Classifier: Programming Language :: Python :: 3
Classifier: License :: OSI Approved :: MIT License
Classifier: Operating System :: OS Independent
Requires-Python: >=3.6
Requires-Dist: greenlet ==3.1.1
Requires-Dist: numpy ==2.1.3
Requires-Dist: pandas ==2.2.3
Requires-Dist: pyodbc ==5.2.0
Requires-Dist: python-dateutil ==2.9.0.post0
Requires-Dist: python-dotenv ==1.0.1
Requires-Dist: pytz ==2024.2
Requires-Dist: six ==1.16.0
Requires-Dist: SQLAlchemy ==2.0.36
Requires-Dist: tabulate ==0.9.0
Requires-Dist: typing-extensions ==4.12.2
Requires-Dist: tzdata ==2024.2
